flask_shorturl.py
Flask_ShortUrl-0.2.0.dist-info/DESCRIPTION.rst
Flask_ShortUrl-0.2.0.dist-info/METADATA
Flask_ShortUrl-0.2.0.dist-info/RECORD
Flask_ShortUrl-0.2.0.dist-info/WHEEL
Flask_ShortUrl-0.2.0.dist-info/metadata.json
Flask_ShortUrl-0.2.0.dist-info/top_level.txt
