Metadata-Version: 2.0
Name: Flask-ShortUrl
Version: 0.2.0
Summary: Short URL generaotr for Flask
Home-page: https://github.com/lepture/flask-shorturl
Author: Hsiaoming Yang
Author-email: me@lepture.com
License: Copyright (c) 2013, Hsiaoming Yang
Requires-Dist: Flask
